travelpy/__init__.py
travelpy/exceptions.py
travelpy/automation/__init__.py
travelpy/beam/__init__.py
travelpy/beam/beam.py
travelpy/beam/conversion.py
travelpy/beamline/__init__.py
travelpy/beamline/core.py
travelpy/beamline/exceptions.py
travelpy/beamline/validation.py
travelpy/config/__init__.py
travelpy/config/column_mappings.py
travelpy/config/paths.py
travelpy/config/settings.py
travelpy/interface/__init__.py
travelpy/results/_generated_properties.py
travelpy/results/parsers.py
travelpy/results/result.py
travelpy/simulation/__init__.py
travelpy/simulation/runner.py
travelpy/utils/__init__.py
travelpy/utils/constants.py
travelpy/utils/physics.py
travelpy-0.1.1.dist-info/licenses/LICENSE
travelpy-0.1.1.dist-info/METADATA
travelpy-0.1.1.dist-info/WHEEL
travelpy-0.1.1.dist-info/top_level.txt
travelpy-0.1.1.dist-info/RECORD
