Metadata-Version: 2.4
Name: travelpy
Version: 0.1.1
Summary: Python wrapper for TRAVEL particle tracking simulations
Author-email: Veliko Dimov <veliko.dimov@protonmail.com>
License: MIT
Project-URL: Homepage, https://github.com/velikodimov/travelpy
Project-URL: Repository, https://github.com/velikodimov/travelpy
Project-URL: Documentation, https://velikodimov.github.io/travelpy
Project-URL: Issues, https://github.com/velikodimov/travelpy/issues
Classifier: Development Status :: 4 - Beta
Classifier: Intended Audience :: Science/Research
Classifier: License :: OSI Approved :: MIT License
Classifier: Programming Language :: Python :: 3
Classifier: Programming Language :: Python :: 3.10
Classifier: Programming Language :: Python :: 3.11
Classifier: Programming Language :: Python :: 3.12
Classifier: Programming Language :: Python :: 3.13
Classifier: Topic :: Scientific/Engineering :: Physics
Requires-Python: >=3.10
License-File: LICENSE
Requires-Dist: numpy>=1.20
Requires-Dist: matplotlib>=3.5
Requires-Dist: pandas>=2.1
Provides-Extra: test
Requires-Dist: pytest>=7.0; extra == "test"
Requires-Dist: pytest-cov; extra == "test"
Requires-Dist: pytest-mock; extra == "test"
Requires-Dist: pytest-timeout; extra == "test"
Requires-Dist: hypothesis; extra == "test"
Provides-Extra: dev
Requires-Dist: ruff; extra == "dev"
Requires-Dist: black; extra == "dev"
Requires-Dist: pre-commit; extra == "dev"
Provides-Extra: docs
Requires-Dist: mkdocs; extra == "docs"
Requires-Dist: mkdocs-material; extra == "docs"
Dynamic: license-file
